datadog_checks/mergify/__about__.py
datadog_checks/mergify/__init__.py
datadog_checks/mergify/check.py
datadog_checks/mergify/config_models/__init__.py
datadog_checks/mergify/config_models/defaults.py
datadog_checks/mergify/config_models/instance.py
datadog_checks/mergify/config_models/shared.py
datadog_checks/mergify/config_models/validators.py
datadog_checks/mergify/data/conf.yaml.example
datadog_mergify-0.0.1.dist-info/METADATA
datadog_mergify-0.0.1.dist-info/WHEEL
datadog_mergify-0.0.1.dist-info/RECORD
