Metadata-Version: 2.1
Name: datadog-mergify
Version: 0.0.1
Summary: The Mergify check
Project-URL: Source, https://github.com/DataDog/integrations-extras
Author-email: Mergify <support@mergify.com>
License: BSD-3-Clause
Keywords: datadog,datadog agent,datadog check,mergify
Classifier: Development Status :: 5 - Production/Stable
Classifier: Intended Audience :: Developers
Classifier: Intended Audience :: System Administrators
Classifier: License :: OSI Approved :: BSD License
Classifier: Programming Language :: Python :: 3.8
Classifier: Topic :: System :: Monitoring
Requires-Python: >=3.8
Requires-Dist: datadog-checks-base>=25.1.0
Provides-Extra: deps
